jaws_libp/__init__.py
jaws_libp/clients.py
jaws_libp/console.py
jaws_libp/entities.py
jaws_libp/eventsource.py
jaws_libp/avro/__init__.py
jaws_libp/avro/schema-registry.json
jaws_libp/avro/serde.py
jaws_libp/avro/topics.json
jaws_libp/avro/schemas/Alarm.avsc
jaws_libp/avro/schemas/AlarmAction.avsc
jaws_libp/avro/schemas/AlarmActivationUnion.avsc
jaws_libp/avro/schemas/AlarmLocation.avsc
jaws_libp/avro/schemas/AlarmOverrideKey.avsc
jaws_libp/avro/schemas/AlarmOverrideSet.avsc
jaws_libp/avro/schemas/AlarmOverrideUnion.avsc
jaws_libp/avro/schemas/AlarmState.avsc
jaws_libp/avro/schemas/AlarmSystem.avsc
jaws_libp/avro/schemas/DisabledOverride.avsc
jaws_libp/avro/schemas/EffectiveAlarm.avsc
jaws_libp/avro/schemas/EffectiveNotification.avsc
jaws_libp/avro/schemas/EffectiveRegistration.avsc
jaws_libp/avro/schemas/FilteredOverride.avsc
jaws_libp/avro/schemas/IntermediateMonolog.avsc
jaws_libp/avro/schemas/LatchedOverride.avsc
jaws_libp/avro/schemas/MaskedOverride.avsc
jaws_libp/avro/schemas/OffDelayedOverride.avsc
jaws_libp/avro/schemas/OnDelayedOverride.avsc
jaws_libp/avro/schemas/OverrideList.avsc
jaws_libp/avro/schemas/ProcessorTransitions.avsc
jaws_libp/avro/schemas/ShelvedOverride.avsc
jaws_libp/avro/schemas/__init__.py
jaws_libp/scripts/__init__.py
jaws_libp/scripts/broker/__init__.py
jaws_libp/scripts/broker/create_topics.py
jaws_libp/scripts/broker/delete_topics.py
jaws_libp/scripts/broker/describe_topics.py
jaws_libp/scripts/broker/list_topics.py
jaws_libp/scripts/broker/show_consumer_groups.py
jaws_libp/scripts/client/__init__.py
jaws_libp/scripts/client/list_actions.py
jaws_libp/scripts/client/list_activations.py
jaws_libp/scripts/client/list_alarms.py
jaws_libp/scripts/client/list_effective_alarms.py
jaws_libp/scripts/client/list_effective_notifications.py
jaws_libp/scripts/client/list_effective_registrations.py
jaws_libp/scripts/client/list_locations.py
jaws_libp/scripts/client/list_overrides.py
jaws_libp/scripts/client/list_systems.py
jaws_libp-5.0.0.dist-info/LICENSE
jaws_libp-5.0.0.dist-info/METADATA
jaws_libp-5.0.0.dist-info/WHEEL
jaws_libp-5.0.0.dist-info/entry_points.txt
jaws_libp-5.0.0.dist-info/top_level.txt
jaws_libp-5.0.0.dist-info/RECORD
