Metadata-Version: 2.1
Name: jaws-libp
Version: 5.0.0
Summary: Jefferson Lab Alarm Warning System API
Author-email: Ryan Slominski <ryans@jlab.org>
License: MIT License
Project-URL: Repository, https://github.com/jeffersonlab/jaws-libp.git
Keywords: kafka,alarm
Classifier: Programming Language :: Python :: 3
Requires-Python: ==3.9.*
License-File: LICENSE
Requires-Dist: confluent-kafka[avro,schema-registry] ==2.3.0
Requires-Dist: psutil ==5.9.8
Requires-Dist: tabulate ==0.9.0
Requires-Dist: requests ==2.31.0
Requires-Dist: click ==7.1.2
Provides-Extra: dev
Requires-Dist: build ==1.1.1 ; extra == 'dev'
Requires-Dist: pytest ==7.4.4 ; extra == 'dev'
Requires-Dist: pytest-env ==1.1.3 ; extra == 'dev'
Requires-Dist: pylint ==2.17.7 ; extra == 'dev'
Requires-Dist: Sphinx ==6.2.1 ; extra == 'dev'
Requires-Dist: sphinx-click ==4.4.0 ; extra == 'dev'
Requires-Dist: sphinx-rtd-theme ==1.3.0 ; extra == 'dev'
Requires-Dist: sphinx-autodoc-typehints ==1.23.0 ; extra == 'dev'
